[
    {
        "Date": "2020-01-01",
        "AvgTemp": 39
    },
    {
        "Date": "2020-01-02",
        "AvgTemp": 41.1
    },
    {
        "Date": "2020-01-03",
        "AvgTemp": 48
    },
    {
        "Date": "2020-01-04",
        "AvgTemp": 45.1
    },
    {
        "Date": "2020-01-05",
        "AvgTemp": 37.1
    },
    {
        "Date": "2020-01-06",
        "AvgTemp": 33.6
    },
    {
        "Date": "2020-01-07",
        "AvgTemp": 38
    },
    {
        "Date": "2020-01-08",
        "AvgTemp": 36.9
    },
    {
        "Date": "2020-01-09",
        "AvgTemp": 28.1
    },
    {
        "Date": "2020-01-10",
        "AvgTemp": 43
    },
    {
        "Date": "2020-01-11",
        "AvgTemp": 59.7
    },
    {
        "Date": "2020-01-12",
        "AvgTemp": 61.7
    },
    {
        "Date": "2020-01-13",
        "AvgTemp": 38.8
    },
    {
        "Date": "2020-01-14",
        "AvgTemp": 39.9
    },
    {
        "Date": "2020-01-15",
        "AvgTemp": 45.2
    },
    {
        "Date": "2020-01-16",
        "AvgTemp": 39.7
    },
    {
        "Date": "2020-01-17",
        "AvgTemp": 20.9
    },
    {
        "Date": "2020-01-18",
        "AvgTemp": 20.6
    },
    {
        "Date": "2020-01-19",
        "AvgTemp": 34.1
    },
    {
        "Date": "2020-01-20",
        "AvgTemp": 23.9
    },
    {
        "Date": "2020-01-21",
        "AvgTemp": 23.2
    },
    {
        "Date": "2020-01-22",
        "AvgTemp": 30.3
    },
    {
        "Date": "2020-01-23",
        "AvgTemp": 38
    },
    {
        "Date": "2020-01-24",
        "AvgTemp": 40.5
    },
    {
        "Date": "2020-01-25",
        "AvgTemp": 44
    },
    {
        "Date": "2020-01-26",
        "AvgTemp": 45.8
    },
    {
        "Date": "2020-01-27",
        "AvgTemp": 42.6
    },
    {
        "Date": "2020-01-28",
        "AvgTemp": 39.6
    },
    {
        "Date": "2020-01-29",
        "AvgTemp": 35.7
    },
    {
        "Date": "2020-01-30",
        "AvgTemp": 28.7
    },
    {
        "Date": "2020-01-31",
        "AvgTemp": 37.2
    },
    {
        "Date": "2020-02-01",
        "AvgTemp": 38.2
    },
    {
        "Date": "2020-02-02",
        "AvgTemp": 39.5
    },
    {
        "Date": "2020-02-03",
        "AvgTemp": 42.2
    },
    {
        "Date": "2020-02-04",
        "AvgTemp": 41.8
    },
    {
        "Date": "2020-02-05",
        "AvgTemp": 39.5
    },
    {
        "Date": "2020-02-06",
        "AvgTemp": 38.2
    },
    {
        "Date": "2020-02-07",
        "AvgTemp": 38.5
    },
    {
        "Date": "2020-02-08",
        "AvgTemp": 30
    },
    {
        "Date": "2020-02-09",
        "AvgTemp": 29.1
    },
    {
        "Date": "2020-02-10",
        "AvgTemp": 44.2
    },
    {
        "Date": "2020-02-11",
        "AvgTemp": 41.9
    },
    {
        "Date": "2020-02-12",
        "AvgTemp": 41.2
    },
    {
        "Date": "2020-02-13",
        "AvgTemp": 38.6
    },
    {
        "Date": "2020-02-14",
        "AvgTemp": 27.3
    },
    {
        "Date": "2020-02-15",
        "AvgTemp": 21.6
    },
    {
        "Date": "2020-02-16",
        "AvgTemp": 38.5
    },
    {
        "Date": "2020-02-17",
        "AvgTemp": 40.7
    },
    {
        "Date": "2020-02-18",
        "AvgTemp": 38.6
    },
    {
        "Date": "2020-02-19",
        "AvgTemp": 41.4
    },
    {
        "Date": "2020-02-20",
        "AvgTemp": 30.4
    },
    {
        "Date": "2020-02-21",
        "AvgTemp": 25.8
    },
    {
        "Date": "2020-02-22",
        "AvgTemp": 38.9
    },
    {
        "Date": "2020-02-23",
        "AvgTemp": 44.8
    },
    {
        "Date": "2020-02-24",
        "AvgTemp": 48.9
    },
    {
        "Date": "2020-02-25",
        "AvgTemp": 46.7
    },
    {
        "Date": "2020-02-26",
        "AvgTemp": 45.3
    },
    {
        "Date": "2020-02-27",
        "AvgTemp": 43.3
    },
    {
        "Date": "2020-02-28",
        "AvgTemp": 33.5
    },
    {
        "Date": "2020-02-29",
        "AvgTemp": 28.8
    },
    {
        "Date": "2020-03-01",
        "AvgTemp": 25.9
    },
    {
        "Date": "2020-03-02",
        "AvgTemp": 39.5
    },
    {
        "Date": "2020-03-03",
        "AvgTemp": 50.7
    },
    {
        "Date": "2020-03-04",
        "AvgTemp": 46
    },
    {
        "Date": "2020-03-05",
        "AvgTemp": 43.3
    },
    {
        "Date": "2020-03-06",
        "AvgTemp": 37.9
    },
    {
        "Date": "2020-03-07",
        "AvgTemp": 35.8
    },
    {
        "Date": "2020-03-08",
        "AvgTemp": 44.5
    },
    {
        "Date": "2020-03-09",
        "AvgTemp": 57.2
    },
    {
        "Date": "2020-03-10",
        "AvgTemp": 52.1
    },
    {
        "Date": "2020-03-11",
        "AvgTemp": 46.9
    },
    {
        "Date": "2020-03-12",
        "AvgTemp": 39.8
    },
    {
        "Date": "2020-03-13",
        "AvgTemp": 47.5
    },
    {
        "Date": "2020-03-14",
        "AvgTemp": 45
    },
    {
        "Date": "2020-03-15",
        "AvgTemp": 38.6
    },
    {
        "Date": "2020-03-16",
        "AvgTemp": 31.3
    },
    {
        "Date": "2020-03-17",
        "AvgTemp": 38.1
    },
    {
        "Date": "2020-03-18",
        "AvgTemp": 42.9
    },
    {
        "Date": "2020-03-19",
        "AvgTemp": 40.6
    },
    {
        "Date": "2020-03-20",
        "AvgTemp": 52.1
    },
    {
        "Date": "2020-03-21",
        "AvgTemp": 43.3
    },
    {
        "Date": "2020-03-22",
        "AvgTemp": 30
    },
    {
        "Date": "2020-03-23",
        "AvgTemp": 34.3
    },
    {
        "Date": "2020-03-24",
        "AvgTemp": 40.7
    },
    {
        "Date": "2020-03-25",
        "AvgTemp": 39.8
    },
    {
        "Date": "2020-03-26",
        "AvgTemp": 39.8
    },
    {
        "Date": "2020-03-27",
        "AvgTemp": 52.3
    },
    {
        "Date": "2020-03-28",
        "AvgTemp": 44.3
    },
    {
        "Date": "2020-03-29",
        "AvgTemp": 41.1
    },
    {
        "Date": "2020-03-30",
        "AvgTemp": 39.5
    },
    {
        "Date": "2020-03-31",
        "AvgTemp": 36
    },
    {
        "Date": "2020-04-01",
        "AvgTemp": 37.5
    },
    {
        "Date": "2020-04-02",
        "AvgTemp": 41.6
    },
    {
        "Date": "2020-04-03",
        "AvgTemp": 43.2
    },
    {
        "Date": "2020-04-04",
        "AvgTemp": 40.6
    },
    {
        "Date": "2020-04-05",
        "AvgTemp": 44.6
    },
    {
        "Date": "2020-04-06",
        "AvgTemp": 51
    },
    {
        "Date": "2020-04-07",
        "AvgTemp": 52.1
    },
    {
        "Date": "2020-04-08",
        "AvgTemp": 45
    },
    {
        "Date": "2020-04-09",
        "AvgTemp": 44.4
    },
    {
        "Date": "2020-04-10",
        "AvgTemp": 42.1
    },
    {
        "Date": "2020-04-11",
        "AvgTemp": 44.2
    },
    {
        "Date": "2020-04-12",
        "AvgTemp": 48.4
    },
    {
        "Date": "2020-04-13",
        "AvgTemp": 56.3
    },
    {
        "Date": "2020-04-14",
        "AvgTemp": 51.7
    },
    {
        "Date": "2020-04-15",
        "AvgTemp": 45.5
    },
    {
        "Date": "2020-04-16",
        "AvgTemp": 40.7
    },
    {
        "Date": "2020-04-17",
        "AvgTemp": 42.1
    },
    {
        "Date": "2020-04-18",
        "AvgTemp": 37.1
    },
    {
        "Date": "2020-04-19",
        "AvgTemp": 48.5
    },
    {
        "Date": "2020-04-20",
        "AvgTemp": 45.9
    },
    {
        "Date": "2020-04-21",
        "AvgTemp": 43.2
    },
    {
        "Date": "2020-04-22",
        "AvgTemp": 38.6
    },
    {
        "Date": "2020-04-23",
        "AvgTemp": 44
    },
    {
        "Date": "2020-04-24",
        "AvgTemp": 42.4
    },
    {
        "Date": "2020-04-25",
        "AvgTemp": 46.8
    },
    {
        "Date": "2020-04-26",
        "AvgTemp": 44.1
    },
    {
        "Date": "2020-04-27",
        "AvgTemp": 40.1
    },
    {
        "Date": "2020-04-28",
        "AvgTemp": 41.3
    },
    {
        "Date": "2020-04-29",
        "AvgTemp": 44.9
    },
    {
        "Date": "2020-04-30",
        "AvgTemp": 45.7
    },
    {
        "Date": "2020-05-01",
        "AvgTemp": 53.3
    },
    {
        "Date": "2020-05-02",
        "AvgTemp": 57.9
    },
    {
        "Date": "2020-05-03",
        "AvgTemp": 65.4
    },
    {
        "Date": "2020-05-04",
        "AvgTemp": 61
    },
    {
        "Date": "2020-05-05",
        "AvgTemp": 50.5
    },
    {
        "Date": "2020-05-06",
        "AvgTemp": 46.1
    },
    {
        "Date": "2020-05-07",
        "AvgTemp": 52.7
    },
    {
        "Date": "2020-05-08",
        "AvgTemp": 49.4
    },
    {
        "Date": "2020-05-09",
        "AvgTemp": 39.9
    },
    {
        "Date": "2020-05-10",
        "AvgTemp": 47.4
    },
    {
        "Date": "2020-05-11",
        "AvgTemp": 50.7
    },
    {
        "Date": "2020-05-12",
        "AvgTemp": 48.3
    },
    {
        "Date": "2020-05-13",
        "AvgTemp": 49.6
    },
    {
        "Date": "2020-05-14",
        "AvgTemp": 58.1
    },
    {
        "Date": "2020-05-15",
        "AvgTemp": 61.1
    },
    {
        "Date": "2020-05-16",
        "AvgTemp": 59.7
    },
    {
        "Date": "2020-05-17",
        "AvgTemp": 55.7
    },
    {
        "Date": "2020-05-18",
        "AvgTemp": 53
    },
    {
        "Date": "2020-05-19",
        "AvgTemp": 50.7
    },
    {
        "Date": "2020-05-20",
        "AvgTemp": 51.4
    },
    {
        "Date": "2020-05-21",
        "AvgTemp": 59.4
    },
    {
        "Date": "2020-05-22",
        "AvgTemp": 69.3
    },
    {
        "Date": "2020-05-23",
        "AvgTemp": 57.9
    },
    {
        "Date": "2020-05-24",
        "AvgTemp": 49.7
    },
    {
        "Date": "2020-05-25",
        "AvgTemp": 50.8
    },
    {
        "Date": "2020-05-26",
        "AvgTemp": 58.1
    },
    {
        "Date": "2020-05-27",
        "AvgTemp": 71
    },
    {
        "Date": "2020-05-28",
        "AvgTemp": 70.7
    },
    {
        "Date": "2020-05-29",
        "AvgTemp": 73
    },
    {
        "Date": "2020-05-30",
        "AvgTemp": 72.9
    },
    {
        "Date": "2020-05-31",
        "AvgTemp": 61.8
    },
    {
        "Date": "2020-06-01",
        "AvgTemp": 56.2
    },
    {
        "Date": "2020-06-02",
        "AvgTemp": 56.6
    },
    {
        "Date": "2020-06-03",
        "AvgTemp": 67.1
    },
    {
        "Date": "2020-06-04",
        "AvgTemp": 73.7
    },
    {
        "Date": "2020-06-05",
        "AvgTemp": 72.4
    },
    {
        "Date": "2020-06-06",
        "AvgTemp": 73
    },
    {
        "Date": "2020-06-07",
        "AvgTemp": 60.1
    },
    {
        "Date": "2020-06-08",
        "AvgTemp": 67.2
    },
    {
        "Date": "2020-06-09",
        "AvgTemp": 66.5
    },
    {
        "Date": "2020-06-10",
        "AvgTemp": 61.5
    },
    {
        "Date": "2020-06-11",
        "AvgTemp": 68.2
    },
    {
        "Date": "2020-06-12",
        "AvgTemp": 74.1
    },
    {
        "Date": "2020-06-13",
        "AvgTemp": 63.1
    },
    {
        "Date": "2020-06-14",
        "AvgTemp": 59.2
    },
    {
        "Date": "2020-06-15",
        "AvgTemp": 59
    },
    {
        "Date": "2020-06-16",
        "AvgTemp": 62.7
    },
    {
        "Date": "2020-06-17",
        "AvgTemp": 65.1
    },
    {
        "Date": "2020-06-18",
        "AvgTemp": 73.4
    },
    {
        "Date": "2020-06-19",
        "AvgTemp": 77.2
    },
    {
        "Date": "2020-06-20",
        "AvgTemp": 80
    },
    {
        "Date": "2020-06-21",
        "AvgTemp": 76.9
    },
    {
        "Date": "2020-06-22",
        "AvgTemp": 65.9
    },
    {
        "Date": "2020-06-23",
        "AvgTemp": 74.3
    },
    {
        "Date": "2020-06-24",
        "AvgTemp": 76.7
    },
    {
        "Date": "2020-06-25",
        "AvgTemp": 76.8
    },
    {
        "Date": "2020-06-26",
        "AvgTemp": 75.4
    },
    {
        "Date": "2020-06-27",
        "AvgTemp": 73
    },
    {
        "Date": "2020-06-28",
        "AvgTemp": 69.3
    },
    {
        "Date": "2020-06-29",
        "AvgTemp": 66.3
    },
    {
        "Date": "2020-06-30",
        "AvgTemp": 64.3
    },
    {
        "Date": "2020-07-01",
        "AvgTemp": 66.5
    },
    {
        "Date": "2020-07-02",
        "AvgTemp": 73.8
    },
    {
        "Date": "2020-07-03",
        "AvgTemp": 68.7
    },
    {
        "Date": "2020-07-04",
        "AvgTemp": 65.3
    },
    {
        "Date": "2020-07-05",
        "AvgTemp": 70.6
    },
    {
        "Date": "2020-07-06",
        "AvgTemp": 66
    },
    {
        "Date": "2020-07-07",
        "AvgTemp": 69
    },
    {
        "Date": "2020-07-08",
        "AvgTemp": 75.8
    },
    {
        "Date": "2020-07-09",
        "AvgTemp": 78
    },
    {
        "Date": "2020-07-10",
        "AvgTemp": 72.2
    },
    {
        "Date": "2020-07-11",
        "AvgTemp": 78.7
    },
    {
        "Date": "2020-07-12",
        "AvgTemp": 80.3
    },
    {
        "Date": "2020-07-13",
        "AvgTemp": 75.6
    },
    {
        "Date": "2020-07-14",
        "AvgTemp": 70.3
    },
    {
        "Date": "2020-07-15",
        "AvgTemp": 65.1
    },
    {
        "Date": "2020-07-16",
        "AvgTemp": 64.5
    },
    {
        "Date": "2020-07-17",
        "AvgTemp": 65.7
    },
    {
        "Date": "2020-07-18",
        "AvgTemp": 78.5
    },
    {
        "Date": "2020-07-19",
        "AvgTemp": 82.2
    },
    {
        "Date": "2020-07-20",
        "AvgTemp": 83.4
    },
    {
        "Date": "2020-07-21",
        "AvgTemp": 82.8
    },
    {
        "Date": "2020-07-22",
        "AvgTemp": 72.5
    },
    {
        "Date": "2020-07-23",
        "AvgTemp": 75.9
    },
    {
        "Date": "2020-07-24",
        "AvgTemp": 74
    },
    {
        "Date": "2020-07-25",
        "AvgTemp": 76.7
    },
    {
        "Date": "2020-07-26",
        "AvgTemp": 82.5
    },
    {
        "Date": "2020-07-27",
        "AvgTemp": 86.1
    },
    {
        "Date": "2020-07-28",
        "AvgTemp": 85.8
    },
    {
        "Date": "2020-07-29",
        "AvgTemp": 79.3
    },
    {
        "Date": "2020-07-30",
        "AvgTemp": 77.8
    },
    {
        "Date": "2020-07-31",
        "AvgTemp": 74.1
    },
    {
        "Date": "2020-08-01",
        "AvgTemp": 75.4
    },
    {
        "Date": "2020-08-02",
        "AvgTemp": 77.2
    },
    {
        "Date": "2020-08-03",
        "AvgTemp": 83.8
    },
    {
        "Date": "2020-08-04",
        "AvgTemp": 74.2
    },
    {
        "Date": "2020-08-05",
        "AvgTemp": 80.3
    },
    {
        "Date": "2020-08-06",
        "AvgTemp": 75.8
    },
    {
        "Date": "2020-08-07",
        "AvgTemp": 69.7
    },
    {
        "Date": "2020-08-08",
        "AvgTemp": 71
    },
    {
        "Date": "2020-08-09",
        "AvgTemp": 77.6
    },
    {
        "Date": "2020-08-10",
        "AvgTemp": 82.4
    },
    {
        "Date": "2020-08-11",
        "AvgTemp": 82
    },
    {
        "Date": "2020-08-12",
        "AvgTemp": 81
    },
    {
        "Date": "2020-08-13",
        "AvgTemp": 77.4
    },
    {
        "Date": "2020-08-14",
        "AvgTemp": 72.7
    },
    {
        "Date": "2020-08-15",
        "AvgTemp": 67.6
    },
    {
        "Date": "2020-08-16",
        "AvgTemp": 66.7
    },
    {
        "Date": "2020-08-17",
        "AvgTemp": 65.8
    },
    {
        "Date": "2020-08-18",
        "AvgTemp": 74.5
    },
    {
        "Date": "2020-08-19",
        "AvgTemp": 68.7
    },
    {
        "Date": "2020-08-20",
        "AvgTemp": 70.5
    },
    {
        "Date": "2020-08-21",
        "AvgTemp": 76.1
    },
    {
        "Date": "2020-08-22",
        "AvgTemp": 73.7
    },
    {
        "Date": "2020-08-23",
        "AvgTemp": 72.2
    },
    {
        "Date": "2020-08-24",
        "AvgTemp": 76
    },
    {
        "Date": "2020-08-25",
        "AvgTemp": 78.2
    },
    {
        "Date": "2020-08-26",
        "AvgTemp": 67.8
    },
    {
        "Date": "2020-08-27",
        "AvgTemp": 62.9
    },
    {
        "Date": "2020-08-28",
        "AvgTemp": 68.6
    },
    {
        "Date": "2020-08-29",
        "AvgTemp": 71.3
    },
    {
        "Date": "2020-08-30",
        "AvgTemp": 70.1
    },
    {
        "Date": "2020-08-31",
        "AvgTemp": 65
    },
    {
        "Date": "2020-09-01",
        "AvgTemp": 66
    },
    {
        "Date": "2020-09-02",
        "AvgTemp": 65.8
    },
    {
        "Date": "2020-09-03",
        "AvgTemp": 70.8
    },
    {
        "Date": "2020-09-04",
        "AvgTemp": 75.1
    },
    {
        "Date": "2020-09-05",
        "AvgTemp": 69.3
    },
    {
        "Date": "2020-09-06",
        "AvgTemp": 68.4
    },
    {
        "Date": "2020-09-07",
        "AvgTemp": 70
    },
    {
        "Date": "2020-09-08",
        "AvgTemp": 69.1
    },
    {
        "Date": "2020-09-09",
        "AvgTemp": 69.9
    },
    {
        "Date": "2020-09-10",
        "AvgTemp": 74
    },
    {
        "Date": "2020-09-11",
        "AvgTemp": 64.2
    },
    {
        "Date": "2020-09-12",
        "AvgTemp": 59.9
    },
    {
        "Date": "2020-09-13",
        "AvgTemp": 64.3
    },
    {
        "Date": "2020-09-14",
        "AvgTemp": 68.4
    },
    {
        "Date": "2020-09-15",
        "AvgTemp": 55.8
    },
    {
        "Date": "2020-09-16",
        "AvgTemp": 61.9
    },
    {
        "Date": "2020-09-17",
        "AvgTemp": 67.3
    },
    {
        "Date": "2020-09-18",
        "AvgTemp": 59.5
    },
    {
        "Date": "2020-09-19",
        "AvgTemp": 53
    },
    {
        "Date": "2020-09-20",
        "AvgTemp": 51.9
    },
    {
        "Date": "2020-09-21",
        "AvgTemp": 53.1
    },
    {
        "Date": "2020-09-22",
        "AvgTemp": 55.8
    },
    {
        "Date": "2020-09-23",
        "AvgTemp": 66.1
    },
    {
        "Date": "2020-09-24",
        "AvgTemp": 69.2
    },
    {
        "Date": "2020-09-25",
        "AvgTemp": 63.6
    },
    {
        "Date": "2020-09-26",
        "AvgTemp": 64.7
    },
    {
        "Date": "2020-09-27",
        "AvgTemp": 68.7
    },
    {
        "Date": "2020-09-28",
        "AvgTemp": 69.6
    },
    {
        "Date": "2020-09-29",
        "AvgTemp": 68.8
    },
    {
        "Date": "2020-09-30",
        "AvgTemp": 69.2
    },
    {
        "Date": "2020-10-01",
        "AvgTemp": 65.4
    },
    {
        "Date": "2020-10-02",
        "AvgTemp": 59.1
    },
    {
        "Date": "2020-10-03",
        "AvgTemp": 55.9
    },
    {
        "Date": "2020-10-04",
        "AvgTemp": 55.9
    },
    {
        "Date": "2020-10-05",
        "AvgTemp": 56.6
    },
    {
        "Date": "2020-10-06",
        "AvgTemp": 58.8
    },
    {
        "Date": "2020-10-07",
        "AvgTemp": 61.7
    },
    {
        "Date": "2020-10-08",
        "AvgTemp": 56
    },
    {
        "Date": "2020-10-09",
        "AvgTemp": 51.8
    },
    {
        "Date": "2020-10-10",
        "AvgTemp": 65.4
    },
    {
        "Date": "2020-10-11",
        "AvgTemp": 57.3
    },
    {
        "Date": "2020-10-12",
        "AvgTemp": 52.7
    },
    {
        "Date": "2020-10-13",
        "AvgTemp": 54.7
    },
    {
        "Date": "2020-10-14",
        "AvgTemp": 58.4
    },
    {
        "Date": "2020-10-15",
        "AvgTemp": 59.8
    },
    {
        "Date": "2020-10-16",
        "AvgTemp": 59.1
    },
    {
        "Date": "2020-10-17",
        "AvgTemp": 49.9
    },
    {
        "Date": "2020-10-18",
        "AvgTemp": 49.5
    },
    {
        "Date": "2020-10-19",
        "AvgTemp": 51.3
    },
    {
        "Date": "2020-10-20",
        "AvgTemp": 57.3
    },
    {
        "Date": "2020-10-21",
        "AvgTemp": 58.8
    },
    {
        "Date": "2020-10-22",
        "AvgTemp": 60.4
    },
    {
        "Date": "2020-10-23",
        "AvgTemp": 57.1
    },
    {
        "Date": "2020-10-24",
        "AvgTemp": 58.9
    },
    {
        "Date": "2020-10-25",
        "AvgTemp": 46.1
    },
    {
        "Date": "2020-10-26",
        "AvgTemp": 51.2
    },
    {
        "Date": "2020-10-27",
        "AvgTemp": 50.7
    },
    {
        "Date": "2020-10-28",
        "AvgTemp": 46.5
    },
    {
        "Date": "2020-10-29",
        "AvgTemp": 46.2
    },
    {
        "Date": "2020-10-30",
        "AvgTemp": 33.9
    },
    {
        "Date": "2020-10-31",
        "AvgTemp": 34.2
    },
    {
        "Date": "2020-11-01",
        "AvgTemp": 42.2
    },
    {
        "Date": "2020-11-02",
        "AvgTemp": 38.4
    },
    {
        "Date": "2020-11-03",
        "AvgTemp": 37.4
    },
    {
        "Date": "2020-11-04",
        "AvgTemp": 43.8
    },
    {
        "Date": "2020-11-05",
        "AvgTemp": 58.5
    },
    {
        "Date": "2020-11-06",
        "AvgTemp": 61.2
    },
    {
        "Date": "2020-11-07",
        "AvgTemp": 62.3
    },
    {
        "Date": "2020-11-08",
        "AvgTemp": 57.2
    },
    {
        "Date": "2020-11-09",
        "AvgTemp": 51.2
    },
    {
        "Date": "2020-11-10",
        "AvgTemp": 60.5
    },
    {
        "Date": "2020-11-11",
        "AvgTemp": 65.2
    },
    {
        "Date": "2020-11-12",
        "AvgTemp": 57.6
    },
    {
        "Date": "2020-11-13",
        "AvgTemp": 45.8
    },
    {
        "Date": "2020-11-14",
        "AvgTemp": 43.1
    },
    {
        "Date": "2020-11-15",
        "AvgTemp": 43.7
    },
    {
        "Date": "2020-11-16",
        "AvgTemp": 48.7
    },
    {
        "Date": "2020-11-17",
        "AvgTemp": 42.1
    },
    {
        "Date": "2020-11-18",
        "AvgTemp": 29.6
    },
    {
        "Date": "2020-11-19",
        "AvgTemp": 33.7
    },
    {
        "Date": "2020-11-20",
        "AvgTemp": 53.3
    },
    {
        "Date": "2020-11-21",
        "AvgTemp": 53.3
    },
    {
        "Date": "2020-11-22",
        "AvgTemp": 42.1
    },
    {
        "Date": "2020-11-23",
        "AvgTemp": 47.3
    },
    {
        "Date": "2020-11-24",
        "AvgTemp": 36.9
    },
    {
        "Date": "2020-11-25",
        "AvgTemp": 38.9
    },
    {
        "Date": "2020-11-26",
        "AvgTemp": 49.8
    },
    {
        "Date": "2020-11-27",
        "AvgTemp": 49.4
    },
    {
        "Date": "2020-11-28",
        "AvgTemp": 47.4
    },
    {
        "Date": "2020-11-29",
        "AvgTemp": 43.9
    },
    {
        "Date": "2020-11-30",
        "AvgTemp": 50.3
    },
    {
        "Date": "2020-12-01",
        "AvgTemp": 55.4
    },
    {
        "Date": "2020-12-02",
        "AvgTemp": 39.7
    },
    {
        "Date": "2020-12-03",
        "AvgTemp": 41.4
    },
    {
        "Date": "2020-12-04",
        "AvgTemp": 48.7
    },
    {
        "Date": "2020-12-05",
        "AvgTemp": 39.4
    },
    {
        "Date": "2020-12-06",
        "AvgTemp": 33.5
    },
    {
        "Date": "2020-12-07",
        "AvgTemp": 29.7
    },
    {
        "Date": "2020-12-08",
        "AvgTemp": 28.6
    },
    {
        "Date": "2020-12-09",
        "AvgTemp": 30.8
    },
    {
        "Date": "2020-12-10",
        "AvgTemp": 38.4
    },
    {
        "Date": "2020-12-11",
        "AvgTemp": 40.9
    },
    {
        "Date": "2020-12-12",
        "AvgTemp": 42.3
    },
    {
        "Date": "2020-12-13",
        "AvgTemp": 47.2
    },
    {
        "Date": "2020-12-14",
        "AvgTemp": 36.1
    },
    {
        "Date": "2020-12-15",
        "AvgTemp": 31.3
    },
    {
        "Date": "2020-12-16",
        "AvgTemp": 23
    },
    {
        "Date": "2020-12-17",
        "AvgTemp": 24.8
    },
    {
        "Date": "2020-12-18",
        "AvgTemp": 25.4
    },
    {
        "Date": "2020-12-19",
        "AvgTemp": 23.8
    },
    {
        "Date": "2020-12-20",
        "AvgTemp": 30.6
    },
    {
        "Date": "2020-12-21",
        "AvgTemp": 33.2
    },
    {
        "Date": "2020-12-22",
        "AvgTemp": 38.2
    },
    {
        "Date": "2020-12-23",
        "AvgTemp": 34.2
    },
    {
        "Date": "2020-12-24",
        "AvgTemp": 43.2
    },
    {
        "Date": "2020-12-25",
        "AvgTemp": 51.9
    },
    {
        "Date": "2020-12-26",
        "AvgTemp": 32
    },
    {
        "Date": "2020-12-27",
        "AvgTemp": 31.2
    },
    {
        "Date": "2020-12-28",
        "AvgTemp": 39.2
    },
    {
        "Date": "2020-12-29",
        "AvgTemp": 33.2
    },
    {
        "Date": "2020-12-30",
        "AvgTemp": 31.2
    },
    {
        "Date": "2020-12-31",
        "AvgTemp": 41.4
    }
]